setup.py
client/__init__.py
client/client.py
client/descriptors/__init__.py
client/descriptors/client_descriptor.py
client/gui/__init__.py
client/gui/add_users.py
client/gui/auth.py
client/gui/authorization.py
client/gui/chat_window.py
client/gui/error.py
client/gui/main.py
client/jim/__init__.py
client/jim/error.py
client/jim/settings.py
client/jim/utils.py
client/metaclasses/__init__.py
client/metaclasses/client_meta.py
message_client.egg-info/PKG-INFO
message_client.egg-info/SOURCES.txt
message_client.egg-info/dependency_links.txt
message_client.egg-info/requires.txt
message_client.egg-info/top_level.txt