Metadata-Version: 1.0
Name: message-client
Version: 0.0.1
Summary: message_client
Home-page: UNKNOWN
Author: Oleg
Author-email: test.test@test.com
License: UNKNOWN
Platform: UNKNOWN
